{
  "LEK": "20451f",
  "KGA": "000000",
  "RAT": "981d2f",
  "STO": "012104",
  "SUN": "960000",
  "SVL": "f28845",
  "UME": "000565",
  "ALB": "0c1535",
  "BRO": "035ca8",
  "CIT": "333333",
  "ENK": "850407",
  "ENS": "122345",
  "GEF": "f80e16",
  "GOT": "eb3228",
  "NIC": "333333",
  "MAL": "7c1a14",
  "SKE": "221e1f",
  "SKO": "201c57",
  "TRA": "4d5150",
  "UPP": "c7090f",
  "FRS": "191919",
  "SOD": "333333",
  "ORE": "092d47",
  "GBR": "000066",
  "SWE": "0C1250",
  "POL": "DC143C",
  "TUR": "F31930",
  "SUI": "D52B1E",
  "VIL": "8B2217",
  "EXP": "4B4AA1",
  "MBI": "1E2361",
  "LDC": "0C0A10",
  "VIF": "472F87",
  "default_home": "720928",
  "default_away": "02224e"
}